psiturk/__init__.py
psiturk/__main__.py
psiturk/amt_services.py
psiturk/command_line.py
psiturk/counter.py
psiturk/db.py
psiturk/experiment.py
psiturk/experiment_errors.py
psiturk/experiment_server.py
psiturk/experiment_server_controller.py
psiturk/models.py
psiturk/psiturk_config.py
psiturk/psiturk_org_services.py
psiturk/psiturk_shell.py
psiturk/setup_example.py
psiturk/user_utils.py
psiturk/version.py
psiturk/default_configs/global_config_defaults.txt
psiturk/default_configs/local_config_defaults.txt
psiturk/example/custom.py.txt
psiturk/example/static/favicon.ico
psiturk/example/static/css/bootstrap.min.css
psiturk/example/static/css/style.css
psiturk/example/static/fonts/glyphicons-halflings-regular.eot
psiturk/example/static/fonts/glyphicons-halflings-regular.svg
psiturk/example/static/fonts/glyphicons-halflings-regular.ttf
psiturk/example/static/fonts/glyphicons-halflings-regular.woff
psiturk/example/static/images/university.png
psiturk/example/static/js/task.js
psiturk/example/static/js/utils.js
psiturk/example/static/lib/backbone-min.js
psiturk/example/static/lib/bootstrap.min.js
psiturk/example/static/lib/d3.v3.min.js
psiturk/example/static/lib/jquery-min.js
psiturk/example/static/lib/underscore-min.js
psiturk/example/templates/ad.html
psiturk/example/templates/complete.html
psiturk/example/templates/consent.html
psiturk/example/templates/custom.html
psiturk/example/templates/debriefing.html
psiturk/example/templates/default.html
psiturk/example/templates/error.html
psiturk/example/templates/exp.html
psiturk/example/templates/list.html
psiturk/example/templates/postquestionnaire.html
psiturk/example/templates/stage.html
psiturk/example/templates/thanks.html
psiturk/example/templates/instructions/instruct-1.html
psiturk/example/templates/instructions/instruct-2.html
psiturk/example/templates/instructions/instruct-3.html
psiturk/example/templates/instructions/instruct-ready.html
psiturk_dallinger-3.0.0.dist-info/DESCRIPTION.rst
psiturk_dallinger-3.0.0.dist-info/METADATA
psiturk_dallinger-3.0.0.dist-info/RECORD
psiturk_dallinger-3.0.0.dist-info/WHEEL
psiturk_dallinger-3.0.0.dist-info/entry_points.txt
psiturk_dallinger-3.0.0.dist-info/metadata.json
psiturk_dallinger-3.0.0.dist-info/top_level.txt
